[{"contributor":"Aaron Haines","allDetections":5720,"sppDetections":5720,"detectorNights":72,"detectors":5,"species":8.0},{"contributor":"Aaron Sidder","allDetections":1078,"sppDetections":1078,"detectorNights":472,"detectors":6,"species":12.0},{"contributor":"Abby Tobin","allDetections":91754,"sppDetections":4246,"detectorNights":5022,"detectors":68,"species":10.0},{"contributor":"Adriana Jakobsen","allDetections":14,"sppDetections":14,"detectorNights":3,"detectors":3,"species":8.0},{"contributor":"Alemta Helmig","allDetections":8,"sppDetections":8,"detectorNights":4,"detectors":3,"species":4.0},{"contributor":"Alex Schubert","allDetections":60,"sppDetections":60,"detectorNights":14,"detectors":2,"species":6.0},{"contributor":"Ali Helmig","allDetections":97,"sppDetections":97,"detectorNights":37,"detectors":5,"species":13.0},{"contributor":"Almeta Helmig","allDetections":114,"sppDetections":114,"detectorNights":37,"detectors":23,"species":13.0},{"contributor":"Amanda Adams","allDetections":157,"sppDetections":157,"detectorNights":48,"detectors":12,"species":9.0},{"contributor":"Amanda Chandler","allDetections":10,"sppDetections":10,"detectorNights":7,"detectors":3,"species":6.0},{"contributor":"Amanda Gehrt","allDetections":204,"sppDetections":153,"detectorNights":32,"detectors":8,"species":11.0},{"contributor":"Amy Gaddy","allDetections":1,"sppDetections":1,"detectorNights":1,"detectors":1,"species":1.0},{"contributor":"Andrew Cha","allDetections":72,"sppDetections":72,"detectorNights":16,"detectors":4,"species":10.0},{"contributor":"Andy and Isaiah Eastlake","allDetections":536,"sppDetections":268,"detectorNights":2,"detectors":1,"species":7.0},{"contributor":"Angelica Mendoza","allDetections":25,"sppDetections":25,"detectorNights":20,"detectors":5,"species":7.0},{"contributor":"Angie McIntire","allDetections":2,"sppDetections":2,"detectorNights":1,"detectors":1,"species":2.0},{"contributor":"Ann Berkely","allDetections":73,"sppDetections":73,"detectorNights":10,"detectors":3,"species":13.0},{"contributor":"Ann Berkley","allDetections":571,"sppDetections":91,"detectorNights":3,"detectors":1,"species":6.0},{"contributor":"Annemarie Prince","allDetections":2,"sppDetections":2,"detectorNights":1,"detectors":1,"species":2.0},{"contributor":"Anthony Gray","allDetections":116,"sppDetections":91,"detectorNights":35,"detectors":8,"species":7.0},{"contributor":"Antoinette Sitting Up Perez","allDetections":8,"sppDetections":8,"detectorNights":1,"detectors":1,"species":8.0},{"contributor":"Antoinette Sitting-up","allDetections":1480,"sppDetections":502,"detectorNights":72,"detectors":20,"species":9.0},{"contributor":"Anya Metcalfe","allDetections":201,"sppDetections":201,"detectorNights":41,"detectors":35,"species":19.0},{"contributor":"April Damanti","allDetections":148,"sppDetections":148,"detectorNights":33,"detectors":6,"species":16.0},{"contributor":"Ashley Egan","allDetections":242,"sppDetections":180,"detectorNights":135,"detectors":21,"species":6.0},{"contributor":"Ashlynn Pryal","allDetections":303,"sppDetections":79,"detectorNights":21,"detectors":8,"species":5.0},{"contributor":"Barb Smith","allDetections":108,"sppDetections":94,"detectorNights":15,"detectors":4,"species":13.0},{"contributor":"Barbara Erlandson","allDetections":1846,"sppDetections":923,"detectorNights":9,"detectors":5,"species":9.0},{"contributor":"Barbara Williams","allDetections":8,"sppDetections":8,"detectorNights":3,"detectors":1,"species":5.0},{"contributor":"Becky Abel","allDetections":144257,"sppDetections":4312,"detectorNights":341,"detectors":1,"species":9.0},{"contributor":"Bernice Tannenbaum","allDetections":1,"sppDetections":1,"detectorNights":1,"detectors":1,"species":1.0},{"contributor":"Beth Ward","allDetections":4365,"sppDetections":4091,"detectorNights":1261,"detectors":726,"species":17.0},{"contributor":"Bethany Schulze","allDetections":6,"sppDetections":6,"detectorNights":1,"detectors":1,"species":6.0},{"contributor":"Bill Gorewich","allDetections":142,"sppDetections":71,"detectorNights":3,"detectors":2,"species":5.0},{"contributor":"Bill Haas","allDetections":121,"sppDetections":121,"detectorNights":18,"detectors":8,"species":17.0},{"contributor":"Bill Tietje","allDetections":48988,"sppDetections":3617,"detectorNights":1992,"detectors":38,"species":12.0},{"contributor":"Bonnie Doggett","allDetections":2583,"sppDetections":268,"detectorNights":22,"detectors":9,"species":6.0},{"contributor":"Brain Heeringa","allDetections":116,"sppDetections":116,"detectorNights":48,"detectors":12,"species":6.0},{"contributor":"Brett Hillman","allDetections":56,"sppDetections":56,"detectorNights":53,"detectors":8,"species":6.0},{"contributor":"Brian Heeringa","allDetections":79034,"sppDetections":14224,"detectorNights":583,"detectors":87,"species":7.0},{"contributor":"Brian Meyerriecks","allDetections":5532,"sppDetections":2646,"detectorNights":37,"detectors":1,"species":8.0},{"contributor":"Brianna Gibson","allDetections":25,"sppDetections":25,"detectorNights":22,"detectors":4,"species":6.0},{"contributor":"Brianne Boan","allDetections":494,"sppDetections":156,"detectorNights":6,"detectors":3,"species":5.0},{"contributor":"Bronwyn Hogan","allDetections":12,"sppDetections":12,"detectorNights":4,"detectors":1,"species":6.0},{"contributor":"Brooklyn Reardon","allDetections":50,"sppDetections":43,"detectorNights":24,"detectors":4,"species":7.0},{"contributor":"Bruce Kimmel","allDetections":340,"sppDetections":170,"detectorNights":1,"detectors":1,"species":2.0},{"contributor":"Bruce Miller","allDetections":3,"sppDetections":3,"detectorNights":1,"detectors":1,"species":3.0},{"contributor":"Bryan Hamilton","allDetections":18674,"sppDetections":7516,"detectorNights":141,"detectors":43,"species":15.0},{"contributor":"Burger Paul","allDetections":31520,"sppDetections":8158,"detectorNights":233,"detectors":15,"species":1.0},{"contributor":"Caleb Browning","allDetections":104,"sppDetections":104,"detectorNights":28,"detectors":7,"species":14.0},{"contributor":"Carla De Julio","allDetections":328,"sppDetections":310,"detectorNights":58,"detectors":11,"species":14.0},{"contributor":"Carly Wickhem","allDetections":6,"sppDetections":6,"detectorNights":2,"detectors":2,"species":3.0},{"contributor":"Carol Joseph","allDetections":20069,"sppDetections":9012,"detectorNights":79,"detectors":3,"species":12.0},{"contributor":"Cassandra Marszal","allDetections":251,"sppDetections":219,"detectorNights":36,"detectors":4,"species":13.0},{"contributor":"Cassie Aguillard","allDetections":52,"sppDetections":52,"detectorNights":18,"detectors":5,"species":7.0},{"contributor":"Catherine Johnson","allDetections":5768,"sppDetections":1372,"detectorNights":119,"detectors":22,"species":5.0},{"contributor":"Cathy Flick","allDetections":4,"sppDetections":4,"detectorNights":1,"detectors":1,"species":4.0},{"contributor":"Chelsea Andreozzi","allDetections":121379,"sppDetections":121379,"detectorNights":407,"detectors":49,"species":13.0},{"contributor":"Cheron Ferland","allDetections":1807,"sppDetections":693,"detectorNights":77,"detectors":22,"species":14.0},{"contributor":"Cheyenne Acevedo","allDetections":1,"sppDetections":1,"detectorNights":2,"detectors":2,"species":1.0},{"contributor":"Chris Corben","allDetections":4,"sppDetections":4,"detectorNights":3,"detectors":2,"species":4.0},{"contributor":"Chris Frauenhofer","allDetections":8,"sppDetections":8,"detectorNights":4,"detectors":1,"species":2.0},{"contributor":"Chris Williams","allDetections":307,"sppDetections":106,"detectorNights":5,"detectors":4,"species":5.0},{"contributor":"Christa Rolls","allDetections":30,"sppDetections":30,"detectorNights":24,"detectors":6,"species":5.0},{"contributor":"Christen Long","allDetections":1,"sppDetections":1,"detectorNights":2,"detectors":2,"species":1.0},{"contributor":"Christina Akins","allDetections":898,"sppDetections":780,"detectorNights":168,"detectors":32,"species":20.0},{"contributor":"Christine Swanson","allDetections":82147,"sppDetections":19463,"detectorNights":174,"detectors":18,"species":7.0},{"contributor":"Christopher Hulbert","allDetections":528,"sppDetections":221,"detectorNights":38,"detectors":11,"species":6.0},{"contributor":"Christopher Reddin","allDetections":26,"sppDetections":26,"detectorNights":24,"detectors":6,"species":5.0},{"contributor":"Christopher Williams","allDetections":54,"sppDetections":54,"detectorNights":16,"detectors":4,"species":5.0},{"contributor":"Christy Klinger","allDetections":60,"sppDetections":60,"detectorNights":20,"detectors":5,"species":12.0},{"contributor":"Cindy Myers","allDetections":3,"sppDetections":3,"detectorNights":3,"detectors":1,"species":2.0},{"contributor":"Clarissa Starbuck","allDetections":136983,"sppDetections":929,"detectorNights":370,"detectors":81,"species":4.0},{"contributor":"Claudio Biltoc","allDetections":382,"sppDetections":190,"detectorNights":4,"detectors":2,"species":8.0},{"contributor":"Clay Edmondson","allDetections":650,"sppDetections":650,"detectorNights":195,"detectors":44,"species":11.0},{"contributor":"Colin & June Choo","allDetections":244,"sppDetections":122,"detectorNights":1,"detectors":1,"species":6.0},{"contributor":"Colin Choo","allDetections":186,"sppDetections":93,"detectorNights":1,"detectors":1,"species":8.0},{"contributor":"Cori Lausen","allDetections":151958,"sppDetections":17355,"detectorNights":2087,"detectors":30,"species":16.0},{"contributor":"Corinna Pinzari","allDetections":479722,"sppDetections":239861,"detectorNights":13579,"detectors":32,"species":1.0},{"contributor":"Corrie Laughlin","allDetections":177,"sppDetections":79,"detectorNights":4,"detectors":2,"species":3.0},{"contributor":"Corrina Tapia","allDetections":9,"sppDetections":9,"detectorNights":4,"detectors":2,"species":4.0},{"contributor":"Cory Olson","allDetections":2,"sppDetections":2,"detectorNights":1,"detectors":1,"species":2.0},{"contributor":"Coye Burnett","allDetections":114,"sppDetections":100,"detectorNights":16,"detectors":4,"species":13.0},{"contributor":"Cris Hein","allDetections":446751,"sppDetections":13297,"detectorNights":233,"detectors":2,"species":8.0},{"contributor":"Crissy Bellandi","allDetections":564,"sppDetections":282,"detectorNights":2,"detectors":1,"species":7.0},{"contributor":"Cynthia Myers","allDetections":3,"sppDetections":3,"detectorNights":3,"detectors":2,"species":3.0},{"contributor":"D. Hair","allDetections":101,"sppDetections":101,"detectorNights":16,"detectors":4,"species":13.0},{"contributor":"Damon Cable","allDetections":280,"sppDetections":104,"detectorNights":1,"detectors":1,"species":3.0},{"contributor":"Damon Haan","allDetections":818,"sppDetections":187,"detectorNights":18,"detectors":8,"species":5.0},{"contributor":"Dana Smith","allDetections":32,"sppDetections":10,"detectorNights":2,"detectors":2,"species":4.0},{"contributor":"Dave Miller","allDetections":8183,"sppDetections":3976,"detectorNights":219,"detectors":10,"species":11.0},{"contributor":"David Delmonte","allDetections":1770,"sppDetections":885,"detectorNights":7,"detectors":1,"species":9.0},{"contributor":"Dean Easton","allDetections":3,"sppDetections":3,"detectorNights":1,"detectors":1,"species":3.0},{"contributor":"Debbie Langenfeld","allDetections":7,"sppDetections":7,"detectorNights":1,"detectors":1,"species":7.0},{"contributor":"Dennis Arakelian","allDetections":261,"sppDetections":131,"detectorNights":2,"detectors":1,"species":11.0},{"contributor":"Devon Green","allDetections":1516,"sppDetections":222,"detectorNights":24,"detectors":6,"species":5.0},{"contributor":"Diana Eck","allDetections":312,"sppDetections":312,"detectorNights":30,"detectors":30,"species":15.0},{"contributor":"Dirk Gard","allDetections":44569,"sppDetections":20758,"detectorNights":470,"detectors":30,"species":10.0},{"contributor":"Don Endicott","allDetections":8,"sppDetections":8,"detectorNights":2,"detectors":1,"species":5.0},{"contributor":"Donald DeBolt","allDetections":328,"sppDetections":164,"detectorNights":1,"detectors":1,"species":6.0},{"contributor":"Donald Solick","allDetections":954,"sppDetections":113,"detectorNights":190,"detectors":2,"species":2.0},{"contributor":"Drew Stokes","allDetections":2392,"sppDetections":1209,"detectorNights":204,"detectors":7,"species":10.0},{"contributor":"Dylan Rhea-Fournier","allDetections":8172,"sppDetections":2490,"detectorNights":25,"detectors":12,"species":11.0},{"contributor":"Eliane Montigny","allDetections":3,"sppDetections":3,"detectorNights":1,"detectors":1,"species":3.0},{"contributor":"Elise Stanmyer","allDetections":3,"sppDetections":3,"detectorNights":1,"detectors":1,"species":3.0},{"contributor":"Elizabeth Hood","allDetections":2,"sppDetections":2,"detectorNights":1,"detectors":1,"species":2.0},{"contributor":"Ella Rowan","allDetections":1632,"sppDetections":1090,"detectorNights":289,"detectors":17,"species":8.0},{"contributor":"Ellen Hall","allDetections":3,"sppDetections":3,"detectorNights":2,"detectors":1,"species":3.0},{"contributor":"Emily Chrostowski","allDetections":71,"sppDetections":71,"detectorNights":34,"detectors":8,"species":5.0},{"contributor":"Emily Hagler","allDetections":159,"sppDetections":159,"detectorNights":52,"detectors":13,"species":11.0},{"contributor":"Eric Schroder","allDetections":1,"sppDetections":1,"detectorNights":23,"detectors":1,"species":1.0},{"contributor":"Erin Baerwald","allDetections":12776,"sppDetections":4850,"detectorNights":1250,"detectors":47,"species":3.0},{"contributor":"Erin Wampole","allDetections":2,"sppDetections":2,"detectorNights":1,"detectors":1,"species":2.0},{"contributor":"Evan Standifer","allDetections":181,"sppDetections":181,"detectorNights":40,"detectors":8,"species":14.0},{"contributor":"Evan Surek","allDetections":254,"sppDetections":254,"detectorNights":41,"detectors":7,"species":16.0},{"contributor":"Francisco Anaya","allDetections":198,"sppDetections":184,"detectorNights":22,"detectors":2,"species":15.0},{"contributor":"Frank McLaughlin","allDetections":11310,"sppDetections":5649,"detectorNights":61,"detectors":8,"species":10.0},{"contributor":"Frank Ridgley","allDetections":12,"sppDetections":12,"detectorNights":3,"detectors":3,"species":5.0},{"contributor":"Gail Collins","allDetections":11797,"sppDetections":11797,"detectorNights":334,"detectors":1,"species":14.0},{"contributor":"Gary Kolesar","allDetections":8787,"sppDetections":1855,"detectorNights":209,"detectors":37,"species":7.0},{"contributor":"Gary Libby","allDetections":1,"sppDetections":1,"detectorNights":1,"detectors":1,"species":1.0},{"contributor":"Gordon Watts","allDetections":233,"sppDetections":222,"detectorNights":40,"detectors":8,"species":14.0},{"contributor":"Greg Andrus","allDetections":95,"sppDetections":95,"detectorNights":28,"detectors":7,"species":6.0},{"contributor":"Greg Falxa","allDetections":9,"sppDetections":9,"detectorNights":4,"detectors":4,"species":5.0},{"contributor":"Greg Flood","allDetections":35,"sppDetections":28,"detectorNights":16,"detectors":4,"species":4.0},{"contributor":"Gregg Janos","allDetections":1,"sppDetections":1,"detectorNights":1,"detectors":1,"species":1.0},{"contributor":"Gregg Jennings","allDetections":123,"sppDetections":123,"detectorNights":15,"detectors":4,"species":15.0},{"contributor":"Gregory Flood","allDetections":858,"sppDetections":307,"detectorNights":76,"detectors":21,"species":7.0},{"contributor":"Hannah Miller","allDetections":0,"sppDetections":0,"detectorNights":1,"detectors":1,"species":null},{"contributor":"Heather Gates","allDetections":3,"sppDetections":3,"detectorNights":4,"detectors":1,"species":3.0},{"contributor":"Heather Kaarakka","allDetections":4,"sppDetections":4,"detectorNights":4,"detectors":1,"species":1.0},{"contributor":"Hulbert Christopher","allDetections":262,"sppDetections":56,"detectorNights":2,"detectors":1,"species":4.0},{"contributor":"Idun Guenther","allDetections":424,"sppDetections":189,"detectorNights":31,"detectors":10,"species":6.0},{"contributor":"Ivan Yates","allDetections":27,"sppDetections":27,"detectorNights":15,"detectors":4,"species":8.0},{"contributor":"Ivana Noell","allDetections":67,"sppDetections":57,"detectorNights":12,"detectors":3,"species":10.0},{"contributor":"J. Paul White","allDetections":9,"sppDetections":9,"detectorNights":40,"detectors":5,"species":2.0},{"contributor":"J.Paul White","allDetections":2,"sppDetections":2,"detectorNights":2,"detectors":1,"species":1.0},{"contributor":"James Bettaso","allDetections":84,"sppDetections":84,"detectorNights":16,"detectors":4,"species":12.0},{"contributor":"James McRacken","allDetections":526,"sppDetections":245,"detectorNights":135,"detectors":3,"species":6.0},{"contributor":"Jamie Bettaso","allDetections":319,"sppDetections":319,"detectorNights":48,"detectors":8,"species":14.0},{"contributor":"Janae Thomas","allDetections":394,"sppDetections":293,"detectorNights":53,"detectors":12,"species":15.0},{"contributor":"Jane Van Gunst","allDetections":112,"sppDetections":112,"detectorNights":25,"detectors":10,"species":12.0},{"contributor":"Jane VanGunst","allDetections":49,"sppDetections":49,"detectorNights":13,"detectors":13,"species":13.0},{"contributor":"Janet Debelak Tyburec","allDetections":12672,"sppDetections":4010,"detectorNights":153,"detectors":4,"species":13.0},{"contributor":"Janet Tyburec","allDetections":23,"sppDetections":23,"detectorNights":7,"detectors":1,"species":5.0},{"contributor":"Janie Agyagos","allDetections":504,"sppDetections":432,"detectorNights":83,"detectors":15,"species":18.0},{"contributor":"Jared Tomie","allDetections":23932,"sppDetections":23932,"detectorNights":652,"detectors":5,"species":7.0},{"contributor":"Jason Dungan","allDetections":276,"sppDetections":48,"detectorNights":34,"detectors":9,"species":7.0},{"contributor":"Jason Kelton","allDetections":299,"sppDetections":202,"detectorNights":77,"detectors":20,"species":14.0},{"contributor":"Jason Unruh","allDetections":299784,"sppDetections":126359,"detectorNights":1819,"detectors":20,"species":9.0},{"contributor":"Jason Whittle","allDetections":1,"sppDetections":1,"detectorNights":1,"detectors":1,"species":1.0},{"contributor":"Jason Williams","allDetections":30,"sppDetections":30,"detectorNights":16,"detectors":4,"species":6.0},{"contributor":"Jeannine Sibley","allDetections":2463,"sppDetections":371,"detectorNights":17,"detectors":6,"species":7.0},{"contributor":"Jeff Cordes","allDetections":302,"sppDetections":288,"detectorNights":100,"detectors":25,"species":16.0},{"contributor":"Jeff Jewkes","allDetections":168,"sppDetections":141,"detectorNights":21,"detectors":4,"species":15.0},{"contributor":"Jeff Mach","allDetections":35211,"sppDetections":7366,"detectorNights":18,"detectors":1,"species":10.0},{"contributor":"Jeffrey Clerc","allDetections":3098,"sppDetections":2024,"detectorNights":541,"detectors":2,"species":7.0},{"contributor":"Jen House","allDetections":485,"sppDetections":413,"detectorNights":66,"detectors":15,"species":16.0},{"contributor":"Jenni Jeffers","allDetections":88,"sppDetections":88,"detectorNights":31,"detectors":8,"species":13.0},{"contributor":"Jennifer Gatlin","allDetections":164,"sppDetections":137,"detectorNights":28,"detectors":6,"species":13.0},{"contributor":"Jennifer House","allDetections":47,"sppDetections":37,"detectorNights":12,"detectors":3,"species":9.0},{"contributor":"Jennifer Krauel","allDetections":11149,"sppDetections":5557,"detectorNights":85,"detectors":22,"species":4.0},{"contributor":"Jennifer West","allDetections":39,"sppDetections":39,"detectorNights":11,"detectors":4,"species":11.0},{"contributor":"Jenny Barnett","allDetections":295416,"sppDetections":177544,"detectorNights":4816,"detectors":19,"species":13.0},{"contributor":"Jeremy Cable","allDetections":2617,"sppDetections":672,"detectorNights":80,"detectors":19,"species":6.0},{"contributor":"Jeremy Mears","allDetections":678,"sppDetections":401,"detectorNights":148,"detectors":31,"species":7.0},{"contributor":"Jeremy Sheets","allDetections":2,"sppDetections":2,"detectorNights":13,"detectors":2,"species":1.0},{"contributor":"Jesika Reimer","allDetections":0,"sppDetections":0,"detectorNights":6,"detectors":1,"species":null},{"contributor":"Jessica Ilse","allDetections":428,"sppDetections":214,"detectorNights":229,"detectors":2,"species":1.0},{"contributor":"Jessup Weichelt","allDetections":359,"sppDetections":69,"detectorNights":6,"detectors":6,"species":3.0},{"contributor":"Jhadzia Walton","allDetections":252,"sppDetections":252,"detectorNights":92,"detectors":23,"species":12.0},{"contributor":"Jimmy Gore","allDetections":1,"sppDetections":1,"detectorNights":1,"detectors":1,"species":1.0},{"contributor":"Jocelyn Perez","allDetections":1492,"sppDetections":638,"detectorNights":41,"detectors":11,"species":14.0},{"contributor":"Joe Medley","allDetections":87,"sppDetections":87,"detectorNights":16,"detectors":4,"species":13.0},{"contributor":"Joe Szewczak","allDetections":1,"sppDetections":1,"detectorNights":1,"detectors":1,"species":1.0},{"contributor":"John Ellis","allDetections":510,"sppDetections":177,"detectorNights":3,"detectors":1,"species":7.0},{"contributor":"John Lamb","allDetections":3,"sppDetections":3,"detectorNights":12,"detectors":2,"species":2.0},{"contributor":"John Simmons","allDetections":82,"sppDetections":82,"detectorNights":45,"detectors":4,"species":9.0},{"contributor":"John White","allDetections":429,"sppDetections":137,"detectorNights":5,"detectors":1,"species":7.0},{"contributor":"Jonathan Kauffman","allDetections":476,"sppDetections":238,"detectorNights":3,"detectors":1,"species":7.0},{"contributor":"Jordan Grotts","allDetections":1,"sppDetections":1,"detectorNights":2,"detectors":2,"species":1.0},{"contributor":"Joseph Danielson","allDetections":21943,"sppDetections":8369,"detectorNights":243,"detectors":14,"species":14.0},{"contributor":"Josephine Oley","allDetections":129,"sppDetections":129,"detectorNights":48,"detectors":11,"species":4.0},{"contributor":"Joshua Vance","allDetections":14,"sppDetections":14,"detectorNights":8,"detectors":2,"species":5.0},{"contributor":"Julia Golias","allDetections":132,"sppDetections":132,"detectorNights":16,"detectors":4,"species":14.0},{"contributor":"Kara Akers","allDetections":4,"sppDetections":4,"detectorNights":1,"detectors":1,"species":4.0},{"contributor":"Karen Blejwas","allDetections":6664391,"sppDetections":299539,"detectorNights":42111,"detectors":186,"species":6.0},{"contributor":"Karen Blewjas","allDetections":114,"sppDetections":28,"detectorNights":6,"detectors":6,"species":5.0},{"contributor":"Karrie Lovins","allDetections":5,"sppDetections":5,"detectorNights":3,"detectors":3,"species":3.0},{"contributor":"Kary Schlick","allDetections":812,"sppDetections":755,"detectorNights":230,"detectors":54,"species":17.0},{"contributor":"Kat Perlman","allDetections":68,"sppDetections":68,"detectorNights":16,"detectors":4,"species":11.0},{"contributor":"Kate Yates","allDetections":111,"sppDetections":47,"detectorNights":30,"detectors":4,"species":9.0},{"contributor":"Katelin Cross","allDetections":3,"sppDetections":3,"detectorNights":3,"detectors":2,"species":1.0},{"contributor":"Kathleen Slocum","allDetections":3632,"sppDetections":997,"detectorNights":53,"detectors":14,"species":14.0},{"contributor":"Kathlyn Stauffer","allDetections":0,"sppDetections":0,"detectorNights":2,"detectors":2,"species":null},{"contributor":"Kathy Cain","allDetections":2727,"sppDetections":1354,"detectorNights":16,"detectors":1,"species":8.0},{"contributor":"Katie Rivette","allDetections":57,"sppDetections":57,"detectorNights":12,"detectors":4,"species":13.0},{"contributor":"Katie Teets","allDetections":3,"sppDetections":3,"detectorNights":1,"detectors":1,"species":3.0},{"contributor":"Katrina Schultes","allDetections":26091,"sppDetections":3312,"detectorNights":185,"detectors":10,"species":7.0},{"contributor":"Katrina Smith","allDetections":1178,"sppDetections":816,"detectorNights":88,"detectors":80,"species":16.0},{"contributor":"Katy Fitzgerald","allDetections":34,"sppDetections":34,"detectorNights":20,"detectors":6,"species":9.0},{"contributor":"Keith VanGorden","allDetections":37,"sppDetections":35,"detectorNights":31,"detectors":5,"species":6.0},{"contributor":"Kellie Roussos","allDetections":38496,"sppDetections":807,"detectorNights":234,"detectors":4,"species":11.0},{"contributor":"Kelly Mosinski","allDetections":113,"sppDetections":113,"detectorNights":16,"detectors":4,"species":10.0},{"contributor":"Kelly Niland","allDetections":42,"sppDetections":42,"detectorNights":32,"detectors":8,"species":5.0},{"contributor":"Kelsey Ekholm","allDetections":2730,"sppDetections":1008,"detectorNights":47,"detectors":29,"species":15.0},{"contributor":"Kevin Edwards","allDetections":430,"sppDetections":215,"detectorNights":2,"detectors":2,"species":6.0},{"contributor":"Kevin Heist","allDetections":3443791,"sppDetections":1640748,"detectorNights":33168,"detectors":273,"species":14.0},{"contributor":"Kevin Warner","allDetections":3,"sppDetections":3,"detectorNights":5,"detectors":2,"species":2.0},{"contributor":"Kim Chase","allDetections":8,"sppDetections":8,"detectorNights":1,"detectors":1,"species":8.0},{"contributor":"Kira Ware","allDetections":1,"sppDetections":1,"detectorNights":1,"detectors":1,"species":1.0},{"contributor":"Kirsten Christopherson","allDetections":6431,"sppDetections":6431,"detectorNights":2164,"detectors":311,"species":28.0},{"contributor":"Kristen Rundquist","allDetections":110,"sppDetections":110,"detectorNights":45,"detectors":11,"species":5.0},{"contributor":"Kristen Warren","allDetections":69,"sppDetections":67,"detectorNights":100,"detectors":19,"species":7.0},{"contributor":"Kristin Henderson","allDetections":300,"sppDetections":150,"detectorNights":1,"detectors":1,"species":6.0},{"contributor":"Kurt Licence","allDetections":9,"sppDetections":9,"detectorNights":5,"detectors":2,"species":3.0},{"contributor":"Kyle Crafts","allDetections":10,"sppDetections":10,"detectorNights":8,"detectors":2,"species":3.0},{"contributor":"Kyle Seppanen","allDetections":1,"sppDetections":1,"detectorNights":9,"detectors":1,"species":1.0},{"contributor":"Laine Yandel","allDetections":91,"sppDetections":91,"detectorNights":20,"detectors":4,"species":13.0},{"contributor":"Larry Alvord","allDetections":41,"sppDetections":41,"detectorNights":20,"detectors":8,"species":7.0},{"contributor":"Laura Moreton","allDetections":4,"sppDetections":4,"detectorNights":1,"detectors":1,"species":4.0},{"contributor":"Lauren Hoyle","allDetections":134,"sppDetections":134,"detectorNights":46,"detectors":8,"species":12.0},{"contributor":"Lauren Michelsen","allDetections":697,"sppDetections":175,"detectorNights":36,"detectors":11,"species":5.0},{"contributor":"Lauren Simpson","allDetections":133,"sppDetections":116,"detectorNights":60,"detectors":3,"species":9.0},{"contributor":"Leighlan Prout","allDetections":9454,"sppDetections":2425,"detectorNights":213,"detectors":64,"species":8.0},{"contributor":"Leila Harris","allDetections":12,"sppDetections":12,"detectorNights":5,"detectors":3,"species":6.0},{"contributor":"Les Gyug","allDetections":42012,"sppDetections":5784,"detectorNights":285,"detectors":27,"species":11.0},{"contributor":"Lilian Self","allDetections":158,"sppDetections":158,"detectorNights":52,"detectors":13,"species":5.0},{"contributor":"Linda Angerer","allDetections":253,"sppDetections":200,"detectorNights":39,"detectors":7,"species":14.0},{"contributor":"Liz Revette","allDetections":53116,"sppDetections":22884,"detectorNights":309,"detectors":36,"species":12.0},{"contributor":"Lorraine Ketzler","allDetections":1,"sppDetections":1,"detectorNights":2,"detectors":1,"species":1.0},{"contributor":"Louise McCallie","allDetections":74,"sppDetections":74,"detectorNights":32,"detectors":8,"species":5.0},{"contributor":"Luz DeWit","allDetections":715,"sppDetections":715,"detectorNights":261,"detectors":70,"species":26.0},{"contributor":"Lynda Lafond","allDetections":40,"sppDetections":40,"detectorNights":22,"detectors":4,"species":4.0},{"contributor":"Lynn Robbins","allDetections":1,"sppDetections":1,"detectorNights":1,"detectors":1,"species":1.0},{"contributor":"MacKenzie Hall-NJFW","allDetections":1521,"sppDetections":707,"detectorNights":5,"detectors":2,"species":5.0},{"contributor":"Mackenzie Jeffress","allDetections":69,"sppDetections":69,"detectorNights":32,"detectors":8,"species":9.0},{"contributor":"Maria Immel","allDetections":494,"sppDetections":494,"detectorNights":68,"detectors":16,"species":15.0},{"contributor":"Mark Enders","allDetections":3118,"sppDetections":3118,"detectorNights":20,"detectors":11,"species":16.0},{"contributor":"Mark Gates","allDetections":53,"sppDetections":53,"detectorNights":20,"detectors":5,"species":5.0},{"contributor":"Mark Vukovich","allDetections":199,"sppDetections":126,"detectorNights":65,"detectors":16,"species":9.0},{"contributor":"Mary and Dave Greene","allDetections":158,"sppDetections":79,"detectorNights":1,"detectors":1,"species":5.0},{"contributor":"Masako Wright","allDetections":255,"sppDetections":225,"detectorNights":43,"detectors":5,"species":9.0},{"contributor":"Matt Chaney","allDetections":108,"sppDetections":108,"detectorNights":18,"detectors":3,"species":12.0},{"contributor":"Matt Lau","allDetections":86,"sppDetections":86,"detectorNights":18,"detectors":4,"species":10.0},{"contributor":"Matt Wilson","allDetections":23,"sppDetections":23,"detectorNights":4,"detectors":1,"species":6.0},{"contributor":"Matthew Mogle","allDetections":46,"sppDetections":46,"detectorNights":56,"detectors":15,"species":5.0},{"contributor":"Matthew Zianni","allDetections":96,"sppDetections":96,"detectorNights":24,"detectors":6,"species":14.0},{"contributor":"Meagan Allira","allDetections":4,"sppDetections":4,"detectorNights":1,"detectors":1,"species":4.0},{"contributor":"Megan Foll","allDetections":16,"sppDetections":16,"detectorNights":3,"detectors":2,"species":10.0},{"contributor":"Megan Solus","allDetections":65,"sppDetections":48,"detectorNights":12,"detectors":3,"species":8.0},{"contributor":"Melissa Whittingslow","allDetections":413,"sppDetections":413,"detectorNights":80,"detectors":15,"species":15.0},{"contributor":"Meredith Naughton","allDetections":191,"sppDetections":84,"detectorNights":19,"detectors":6,"species":6.0},{"contributor":"Michael Huhndorf","allDetections":473,"sppDetections":473,"detectorNights":83,"detectors":19,"species":15.0},{"contributor":"Michael O'Farrell","allDetections":46382,"sppDetections":34631,"detectorNights":95,"detectors":86,"species":17.0},{"contributor":"Michael Steck","allDetections":330,"sppDetections":194,"detectorNights":50,"detectors":6,"species":11.0},{"contributor":"Michael Turso","allDetections":917,"sppDetections":917,"detectorNights":423,"detectors":5,"species":6.0},{"contributor":"Michael West","allDetections":15,"sppDetections":15,"detectorNights":12,"detectors":3,"species":4.0},{"contributor":"Miguel Ordenana","allDetections":22623,"sppDetections":11299,"detectorNights":312,"detectors":11,"species":9.0},{"contributor":"Miguel Orde\u00c3\u0083\u00c2\u00b1ana","allDetections":18702,"sppDetections":7449,"detectorNights":5907,"detectors":28,"species":9.0},{"contributor":"Mike Doyle","allDetections":768,"sppDetections":384,"detectorNights":3,"detectors":2,"species":6.0},{"contributor":"Mike O'Farrell","allDetections":1790,"sppDetections":1790,"detectorNights":616,"detectors":31,"species":19.0},{"contributor":"Montana NHP","allDetections":13293368,"sppDetections":3047074,"detectorNights":66293,"detectors":184,"species":8.0},{"contributor":"Monte Kuk","allDetections":232,"sppDetections":188,"detectorNights":67,"detectors":10,"species":10.0},{"contributor":"Monty Sea","allDetections":81,"sppDetections":81,"detectorNights":12,"detectors":3,"species":14.0},{"contributor":"Mony Sea","allDetections":93,"sppDetections":70,"detectorNights":12,"detectors":3,"species":12.0},{"contributor":"Mylea Bayless","allDetections":219,"sppDetections":219,"detectorNights":49,"detectors":1,"species":14.0},{"contributor":"Nadine Hergenrider","allDetections":8158,"sppDetections":1175,"detectorNights":22,"detectors":8,"species":9.0},{"contributor":"Nadja Schmidt","allDetections":7,"sppDetections":7,"detectorNights":93,"detectors":4,"species":4.0},{"contributor":"Nana Chroninger","allDetections":15440,"sppDetections":7712,"detectorNights":55,"detectors":2,"species":12.0},{"contributor":"Nana chroninger","allDetections":324,"sppDetections":162,"detectorNights":1,"detectors":1,"species":7.0},{"contributor":"Nancy Kelly","allDetections":1113,"sppDetections":462,"detectorNights":34,"detectors":9,"species":17.0},{"contributor":"Nate Gwinn","allDetections":61,"sppDetections":61,"detectorNights":45,"detectors":12,"species":6.0},{"contributor":"Nathan Muenks","allDetections":198,"sppDetections":198,"detectorNights":64,"detectors":15,"species":7.0},{"contributor":"Ned Lockwood","allDetections":443,"sppDetections":222,"detectorNights":2,"detectors":1,"species":8.0},{"contributor":"Nicholle Stephens","allDetections":2,"sppDetections":2,"detectorNights":1,"detectors":1,"species":2.0},{"contributor":"Nicole Besler","allDetections":195,"sppDetections":47,"detectorNights":3,"detectors":3,"species":6.0},{"contributor":"Nicole Shutt","allDetections":36,"sppDetections":34,"detectorNights":16,"detectors":4,"species":5.0},{"contributor":"Noelle Ronan","allDetections":20,"sppDetections":20,"detectorNights":3,"detectors":2,"species":8.0},{"contributor":"Paige Howard","allDetections":2,"sppDetections":2,"detectorNights":2,"detectors":1,"species":2.0},{"contributor":"Pam Nankervis","allDetections":384,"sppDetections":384,"detectorNights":148,"detectors":37,"species":6.0},{"contributor":"Pamela Thurston","allDetections":2410,"sppDetections":483,"detectorNights":79,"detectors":15,"species":7.0},{"contributor":"Pan Nankervis","allDetections":96,"sppDetections":39,"detectorNights":6,"detectors":5,"species":5.0},{"contributor":"Pat Barfield","allDetections":1,"sppDetections":1,"detectorNights":1,"detectors":1,"species":1.0},{"contributor":"Paul Burger","allDetections":1338813,"sppDetections":190548,"detectorNights":6227,"detectors":118,"species":5.0},{"contributor":"Paul Kreingold","allDetections":296,"sppDetections":148,"detectorNights":1,"detectors":1,"species":5.0},{"contributor":"Paul Lenza","allDetections":42,"sppDetections":42,"detectorNights":12,"detectors":3,"species":6.0},{"contributor":"Peggy Plass","allDetections":2034,"sppDetections":1015,"detectorNights":21,"detectors":9,"species":9.0},{"contributor":"Penny Hunter","allDetections":5124,"sppDetections":5124,"detectorNights":12,"detectors":4,"species":15.0},{"contributor":"Pete Filicetti","allDetections":84,"sppDetections":42,"detectorNights":1,"detectors":1,"species":6.0},{"contributor":"Pete Johnston","allDetections":508,"sppDetections":485,"detectorNights":114,"detectors":21,"species":13.0},{"contributor":"Peter Johnston","allDetections":55,"sppDetections":55,"detectorNights":10,"detectors":2,"species":10.0},{"contributor":"Phil Huber","allDetections":505,"sppDetections":207,"detectorNights":46,"detectors":10,"species":5.0},{"contributor":"Philip Huber","allDetections":4850,"sppDetections":861,"detectorNights":49,"detectors":21,"species":5.0},{"contributor":"Phillip Huber","allDetections":17272,"sppDetections":3247,"detectorNights":136,"detectors":11,"species":5.0},{"contributor":"Preston Taylor","allDetections":294,"sppDetections":294,"detectorNights":70,"detectors":18,"species":12.0},{"contributor":"Rachel Blakey","allDetections":702,"sppDetections":702,"detectorNights":249,"detectors":83,"species":17.0},{"contributor":"Rahel Sollman","allDetections":42617,"sppDetections":4727,"detectorNights":120,"detectors":27,"species":14.0},{"contributor":"Ray Long","allDetections":104,"sppDetections":92,"detectorNights":43,"detectors":2,"species":8.0},{"contributor":"Rebecca Cook","allDetections":286,"sppDetections":286,"detectorNights":50,"detectors":12,"species":15.0},{"contributor":"Rhonda Stewart","allDetections":151,"sppDetections":125,"detectorNights":42,"detectors":6,"species":11.0},{"contributor":"Richard Dulik","allDetections":698,"sppDetections":349,"detectorNights":7,"detectors":2,"species":6.0},{"contributor":"Richard Winstead","allDetections":1875,"sppDetections":422,"detectorNights":86,"detectors":11,"species":8.0},{"contributor":"Rick Dulik","allDetections":916,"sppDetections":458,"detectorNights":6,"detectors":5,"species":9.0},{"contributor":"Robert Bastarache","allDetections":188,"sppDetections":188,"detectorNights":87,"detectors":15,"species":8.0},{"contributor":"Robert Davies","allDetections":20,"sppDetections":20,"detectorNights":7,"detectors":1,"species":6.0},{"contributor":"Robin Eliason","allDetections":16,"sppDetections":15,"detectorNights":16,"detectors":4,"species":5.0},{"contributor":"Robin Garwood","allDetections":663,"sppDetections":500,"detectorNights":135,"detectors":8,"species":13.0},{"contributor":"Robin Holland","allDetections":32,"sppDetections":32,"detectorNights":12,"detectors":2,"species":5.0},{"contributor":"Rodney Polden","allDetections":1,"sppDetections":1,"detectorNights":2,"detectors":1,"species":1.0},{"contributor":"Roger Rodriguez","allDetections":11921,"sppDetections":9794,"detectorNights":2542,"detectors":1502,"species":15.0},{"contributor":"Roxanne Howe","allDetections":58,"sppDetections":58,"detectorNights":15,"detectors":4,"species":12.0},{"contributor":"Roy Bridgman","allDetections":216,"sppDetections":216,"detectorNights":48,"detectors":12,"species":13.0},{"contributor":"Ryan Blankenship","allDetections":3,"sppDetections":3,"detectorNights":1,"detectors":1,"species":3.0},{"contributor":"Ryan Kaldari","allDetections":116,"sppDetections":25,"detectorNights":23,"detectors":1,"species":4.0},{"contributor":"Ryan Pennesi","allDetections":50,"sppDetections":50,"detectorNights":16,"detectors":4,"species":5.0},{"contributor":"Sam Coleman","allDetections":4,"sppDetections":4,"detectorNights":4,"detectors":4,"species":3.0},{"contributor":"Samantha Marcum","allDetections":263885,"sppDetections":56192,"detectorNights":844,"detectors":4,"species":17.0},{"contributor":"Samuel Schratz","allDetections":462,"sppDetections":219,"detectorNights":38,"detectors":10,"species":15.0},{"contributor":"Sara Soderberg","allDetections":137,"sppDetections":137,"detectorNights":32,"detectors":8,"species":13.0},{"contributor":"Scott Osborn","allDetections":152363,"sppDetections":29853,"detectorNights":323,"detectors":7,"species":11.0},{"contributor":"Scott Rush","allDetections":1,"sppDetections":1,"detectorNights":2,"detectors":1,"species":1.0},{"contributor":"Scott Sheehan","allDetections":105,"sppDetections":105,"detectorNights":45,"detectors":9,"species":7.0},{"contributor":"Sean Vander Hoek","allDetections":298,"sppDetections":149,"detectorNights":1,"detectors":1,"species":6.0},{"contributor":"Shannon Amerine","allDetections":87,"sppDetections":87,"detectorNights":22,"detectors":7,"species":13.0},{"contributor":"Shawn Langston","allDetections":55,"sppDetections":55,"detectorNights":16,"detectors":4,"species":5.0},{"contributor":"Shawn Thomas","allDetections":257888,"sppDetections":29785,"detectorNights":3566,"detectors":12,"species":17.0},{"contributor":"Sinead Borchert","allDetections":42,"sppDetections":42,"detectorNights":16,"detectors":4,"species":5.0},{"contributor":"Stacey Hayden","allDetections":2,"sppDetections":2,"detectorNights":2,"detectors":1,"species":2.0},{"contributor":"Stephanie Brady","allDetections":3,"sppDetections":3,"detectorNights":1,"detectors":1,"species":3.0},{"contributor":"Stephanie Rainey","allDetections":102,"sppDetections":81,"detectorNights":16,"detectors":4,"species":10.0},{"contributor":"Stephen Davenport","allDetections":182,"sppDetections":182,"detectorNights":48,"detectors":12,"species":13.0},{"contributor":"Stephen Najjar","allDetections":86,"sppDetections":86,"detectorNights":25,"detectors":5,"species":8.0},{"contributor":"Steve Anderson","allDetections":349,"sppDetections":313,"detectorNights":94,"detectors":19,"species":14.0},{"contributor":"Steve Norton","allDetections":63,"sppDetections":63,"detectorNights":24,"detectors":6,"species":8.0},{"contributor":"Steven Wetzel","allDetections":1,"sppDetections":1,"detectorNights":1,"detectors":1,"species":1.0},{"contributor":"Steven Zanoni","allDetections":2623,"sppDetections":571,"detectorNights":57,"detectors":11,"species":4.0},{"contributor":"Sue Fox","allDetections":370,"sppDetections":370,"detectorNights":107,"detectors":64,"species":14.0},{"contributor":"Susan Broderick","allDetections":12,"sppDetections":12,"detectorNights":4,"detectors":4,"species":8.0},{"contributor":"Susan Loeb","allDetections":76370,"sppDetections":18593,"detectorNights":470,"detectors":186,"species":9.0},{"contributor":"Susan Sims","allDetections":5938,"sppDetections":2381,"detectorNights":62,"detectors":7,"species":11.0},{"contributor":"Susan Yasuda","allDetections":201,"sppDetections":173,"detectorNights":56,"detectors":9,"species":13.0},{"contributor":"Suzanne DeRosier","allDetections":128,"sppDetections":75,"detectorNights":16,"detectors":4,"species":9.0},{"contributor":"Sydney Bush","allDetections":21,"sppDetections":21,"detectorNights":16,"detectors":4,"species":5.0},{"contributor":"Taylor Brannock","allDetections":59,"sppDetections":59,"detectorNights":16,"detectors":4,"species":6.0},{"contributor":"Ted Weller","allDetections":1769604,"sppDetections":113529,"detectorNights":35145,"detectors":300,"species":24.0},{"contributor":"Theresa Davidson","allDetections":1149,"sppDetections":237,"detectorNights":81,"detectors":20,"species":8.0},{"contributor":"Theresa Lowe","allDetections":310,"sppDetections":290,"detectorNights":62,"detectors":17,"species":15.0},{"contributor":"Thomas Ryon","allDetections":212,"sppDetections":19,"detectorNights":22,"detectors":1,"species":2.0},{"contributor":"Tim Catton","allDetections":4948,"sppDetections":1946,"detectorNights":483,"detectors":98,"species":6.0},{"contributor":"Tim Krynak","allDetections":5,"sppDetections":5,"detectorNights":4,"detectors":3,"species":2.0},{"contributor":"Timothy Catton","allDetections":182,"sppDetections":97,"detectorNights":34,"detectors":9,"species":5.0},{"contributor":"Tina Greenwalt","allDetections":179,"sppDetections":179,"detectorNights":80,"detectors":7,"species":15.0},{"contributor":"Toby Negrin","allDetections":3934,"sppDetections":1679,"detectorNights":48,"detectors":4,"species":9.0},{"contributor":"Todd Johnson","allDetections":816,"sppDetections":778,"detectorNights":131,"detectors":25,"species":15.0},{"contributor":"Todd Mabee","allDetections":233729,"sppDetections":17043,"detectorNights":318,"detectors":2,"species":5.0},{"contributor":"Todd Russel","allDetections":234,"sppDetections":184,"detectorNights":32,"detectors":8,"species":14.0},{"contributor":"Todd Russell","allDetections":542,"sppDetections":519,"detectorNights":64,"detectors":16,"species":15.0},{"contributor":"Todd Stewart","allDetections":206,"sppDetections":173,"detectorNights":72,"detectors":9,"species":8.0},{"contributor":"Tom Malloy","allDetections":113859,"sppDetections":45290,"detectorNights":248,"detectors":4,"species":14.0},{"contributor":"Tom Rickman","allDetections":145,"sppDetections":132,"detectorNights":16,"detectors":4,"species":14.0},{"contributor":"Toni Piaggio","allDetections":5,"sppDetections":5,"detectorNights":63,"detectors":1,"species":2.0},{"contributor":"Tracy Grazia","allDetections":2327,"sppDetections":1033,"detectorNights":416,"detectors":102,"species":9.0},{"contributor":"Trevor Moore","allDetections":450,"sppDetections":450,"detectorNights":76,"detectors":10,"species":11.0},{"contributor":"Trevor Peterson","allDetections":932418,"sppDetections":147286,"detectorNights":17350,"detectors":38,"species":5.0},{"contributor":"Trinity Smith","allDetections":3,"sppDetections":3,"detectorNights":3,"detectors":1,"species":1.0},{"contributor":"Vanessa Armentrout","allDetections":8,"sppDetections":8,"detectorNights":2,"detectors":2,"species":5.0},{"contributor":"Veronica Reed","allDetections":33,"sppDetections":33,"detectorNights":10,"detectors":2,"species":5.0},{"contributor":"Wendy Connally","allDetections":3,"sppDetections":3,"detectorNights":1,"detectors":1,"species":3.0},{"contributor":"William Rainey","allDetections":0,"sppDetections":0,"detectorNights":5,"detectors":1,"species":null},{"contributor":"Zack Steel","allDetections":49531,"sppDetections":49531,"detectorNights":1304,"detectors":194,"species":17.0},{"contributor":"john White","allDetections":310,"sppDetections":85,"detectorNights":1,"detectors":1,"species":2.0},{"contributor":"peggy Plass","allDetections":48,"sppDetections":24,"detectorNights":1,"detectors":1,"species":3.0}]